EcarX8155/__init__.py
EcarX8155/base_function.py
EcarX8155/canoe.py
EcarX8155/read_config.py
EcarX8155-2.0.dist-info/METADATA
EcarX8155-2.0.dist-info/WHEEL
EcarX8155-2.0.dist-info/top_level.txt
EcarX8155-2.0.dist-info/RECORD
