Metadata-Version: 2.1
Name: EcarX8155
Version: 2.0
Summary: platform8155的包
Author: zhuxiaodong
Author-email: zhuxiaodong45@163.com
Classifier: Programming Language :: Python :: 3
Classifier: License :: OSI Approved :: MIT License
Classifier: Operating System :: OS Independent
Requires-Python: >=3
Requires-Dist: pillow
